claude_worktree/__init__.py
claude_worktree/__main__.py
claude_worktree/cli.py
claude_worktree/config.py
claude_worktree/console.py
claude_worktree/constants.py
claude_worktree/cwshare_setup.py
claude_worktree/exceptions.py
claude_worktree/git_utils.py
claude_worktree/helpers.py
claude_worktree/hooks.py
claude_worktree/messages.py
claude_worktree/session_manager.py
claude_worktree/shared_files.py
claude_worktree/slash_command_setup.py
claude_worktree/update.py
claude_worktree/operations/__init__.py
claude_worktree/operations/ai_tools.py
claude_worktree/operations/backup_ops.py
claude_worktree/operations/config_ops.py
claude_worktree/operations/diagnostics.py
claude_worktree/operations/display.py
claude_worktree/operations/git_ops.py
claude_worktree/operations/helpers.py
claude_worktree/operations/stash_ops.py
claude_worktree/operations/worktree_ops.py
claude_worktree/shell_functions/__init__.py
claude_worktree/shell_functions/cw.bash
claude_worktree/shell_functions/cw.fish
claude_worktree/shell_functions/cw.ps1
claude_worktree/slash_commands/__init__.py
claude_worktree/slash_commands/cw.md
claude_worktree/slash_commands/cw/delete.md
claude_worktree/slash_commands/cw/list.md
claude_worktree/slash_commands/cw/merge.md
claude_worktree/slash_commands/cw/new.md
claude_worktree/slash_commands/cw/pr.md
claude_worktree/slash_commands/cw/resume.md
claude_worktree/slash_commands/cw/status.md
claude_worktree-0.10.42.dist-info/METADATA
claude_worktree-0.10.42.dist-info/WHEEL
claude_worktree-0.10.42.dist-info/entry_points.txt
claude_worktree-0.10.42.dist-info/licenses/LICENSE
claude_worktree-0.10.42.dist-info/RECORD
