Metadata-Version: 2.4
Name: claude-worktree
Version: 0.10.42
Summary: CLI tool integrating git worktree with Claude Code for seamless feature development workflows
Project-URL: Homepage, https://github.com/DaveDev42/claude-worktree
Project-URL: Repository, https://github.com/DaveDev42/claude-worktree
Project-URL: Issues, https://github.com/DaveDev42/claude-worktree/issues
Author-email: Dave <dave.dev@icloud.com>
License: BSD-3-Clause
License-File: LICENSE
Keywords: claude,cli,development,git,workflow,worktree
Classifier: Development Status :: 4 - Beta
Classifier: Intended Audience :: Developers
Classifier: License :: OSI Approved :: BSD License
Classifier: Programming Language :: Python :: 3
Classifier: Programming Language :: Python :: 3.11
Classifier: Programming Language :: Python :: 3.12
Classifier: Topic :: Software Development :: Version Control :: Git
Classifier: Topic :: Utilities
Requires-Python: >=3.11
Requires-Dist: httpx>=0.27.0
Requires-Dist: packaging>=24.0
Requires-Dist: rich>=13.0.0
Requires-Dist: typer>=0.12.0
Provides-Extra: dev
Requires-Dist: mypy>=1.8.0; extra == 'dev'
Requires-Dist: pre-commit>=4.0.0; extra == 'dev'
Requires-Dist: pytest-cov>=4.1.0; extra == 'dev'
Requires-Dist: pytest-md>=0.2.0; extra == 'dev'
Requires-Dist: pytest-mock>=3.12.0; extra == 'dev'
Requires-Dist: pytest-xdist>=3.5.0; extra == 'dev'
Requires-Dist: pytest>=8.0.0; extra == 'dev'
Requires-Dist: ruff>=0.3.0; extra == 'dev'
